pyirt/__init__.py
pyirt/_pyirt.py
pyirt/algo.py
pyirt/dao.py
pyirt/logger.py
pyirt/solver/__init__.py
pyirt/solver/model.py
pyirt/solver/optimizer.py
pyirt/solver/theta_estimator.py
pyirt/util/__init__.py
pyirt/util/clib.pyx
pyirt/util/dao.py
pyirt/util/tools.py
pyirt-0.3.4.dist-info/LICENSE.txt
pyirt-0.3.4.dist-info/METADATA
pyirt-0.3.4.dist-info/WHEEL
pyirt-0.3.4.dist-info/top_level.txt
pyirt-0.3.4.dist-info/RECORD
