Metadata-Version: 2.1
Name: pyirt
Version: 0.3.4
Summary: A python implementation of Item Response Theory(IRT), specializing in big dataset
Home-page: https://github.com/junchenfeng/pyirt
Author: Junchen Feng
Author-email: frankfeng.pku@gmail.com
License: MIT
Download-URL: https://github.com/17zuoye/pyirt/archive/v0.3.4.tar.gz
Keywords: IRT,EM,big data
Platform: any
Classifier: Intended Audience :: Developers
Classifier: Operating System :: OS Independent
Classifier: Programming Language :: Python :: 3.6
Requires-Dist: numpy
Requires-Dist: scipy
Requires-Dist: cython
Requires-Dist: pymongo
Requires-Dist: tqdm
Requires-Dist: python-decouple
